datetime_helper/__init__.py
datetime_helper/core.py
tests/__init__.py
tests/test_dateutils.py
python_datetimehelper-0.0.3.dist-info/LICENSE
python_datetimehelper-0.0.3.dist-info/METADATA
python_datetimehelper-0.0.3.dist-info/WHEEL
python_datetimehelper-0.0.3.dist-info/top_level.txt
python_datetimehelper-0.0.3.dist-info/RECORD
